auth_aws_profile/__init__.py
auth_aws_profile/auth_aws_profile.py
auth_aws_profile-0.2.0.dist-info/entry_points.txt
auth_aws_profile-0.2.0.dist-info/LICENSE
auth_aws_profile-0.2.0.dist-info/WHEEL
auth_aws_profile-0.2.0.dist-info/METADATA
auth_aws_profile-0.2.0.dist-info/RECORD
