Metadata-Version: 2.1
Name: auth-aws-profile
Version: 0.2.0
Summary: Updates the configured MFA credentials for AWS services.
Author: kdico
Author-email: 8462911+kdico@users.noreply.github.com
Requires-Python: >=3.12,<4.0
Classifier: Programming Language :: Python :: 3
Requires-Dist: boto3 (>=1.35.5,<2.0.0)
Project-URL: Bug Tracker, https://github.com/kdico/auth-aws-profile/issues
